README.md
setup.cfg
setup.py
configtune/__init__.py
configtune/base_tuner.py
configtune/config_mapping.py
configtune/tuningbayes.py
configtune/tuningdeap.py
configtune.egg-info/PKG-INFO
configtune.egg-info/SOURCES.txt
configtune.egg-info/dependency_links.txt
configtune.egg-info/requires.txt
configtune.egg-info/top_level.txt
test/__init__.py
test/dummy_model.py
test/test_basic_config.py
test/test_full_mlp.py
test/test_logging.py
test/test_no_config.py
test/test_reproducibility.py
test/test_timing.py
test/test_tuningbayes/__init__.py
test/test_tuningbayes/test_population_validity.py
test/test_tuningbayes/test_warm_start_bayes.py
test/test_tuningdeap/__init__.py
test/test_tuningdeap/test_initialize_starting_population.py
test/test_tuningdeap/test_long_generations_for_limits.py
test/test_tuningdeap/test_pop_and_generate.py
test/test_tuningdeap/test_population_size.py
test/test_utils/__init__.py
test/test_utils/test_config_mapping.py
test/test_utils/test_correct_invalid.py
test/test_utils/test_mapping_back.py